intell.py
intell-1.0.0.dist-info/WHEEL
intell-1.0.0.dist-info/METADATA
intell-1.0.0.dist-info/RECORD
